{"lastUsed":1640227670380,"path":"C:\/Users\/Ocean\/Desktop\/HW5","projectCount":22,"recentFiles":[{"path":"\/test_p36\/src\/test_p36","parentWorkspace":"C:\/Users\/Ocean\/Desktop\/HW5","name":"Sample5_13.java","lastModified":1640225206237,"locationURI":"file:\/C:\/Users\/Ocean\/Desktop\/HW5\/test_p36\/src\/test_p36\/Sample5_13.java"},{"path":"\/test_p21\/src\/test_p21","parentWorkspace":"C:\/Users\/Ocean\/Desktop\/HW5","name":"Sample5_6.java","lastModified":1640223264522,"locationURI":"file:\/C:\/Users\/Ocean\/Desktop\/HW5\/test_p21\/src\/test_p21\/Sample5_6.java"},{"path":"\/test_p44\/src\/test_p44","parentWorkspace":"C:\/Users\/Ocean\/Desktop\/HW5","name":"Sample5_15.java","lastModified":1640226181588,"locationURI":"file:\/C:\/Users\/Ocean\/Desktop\/HW5\/test_p44\/src\/test_p44\/Sample5_15.java"},{"path":"\/test_p52\/src\/test_p52","parentWorkspace":"C:\/Users\/Ocean\/Desktop\/HW5","name":"Sample5_20.java","lastModified":1640227508046,"locationURI":"file:\/C:\/Users\/Ocean\/Desktop\/HW5\/test_p52\/src\/test_p52\/Sample5_20.java"},{"path":"\/test_p14\/src\/pc","parentWorkspace":"C:\/Users\/Ocean\/Desktop\/HW5","name":"Car.java","lastModified":1640222816046,"locationURI":"file:\/C:\/Users\/Ocean\/Desktop\/HW5\/test_p14\/src\/pc\/Car.java"},{"path":"\/test_p48\/src\/test_p48","parentWorkspace":"C:\/Users\/Ocean\/Desktop\/HW5","name":"Sample5_18.java","lastModified":1640226914757,"locationURI":"file:\/C:\/Users\/Ocean\/Desktop\/HW5\/test_p48\/src\/test_p48\/Sample5_18.java"},{"path":"\/test_p30\/src\/test_p30","parentWorkspace":"C:\/Users\/Ocean\/Desktop\/HW5","name":"Sample5_9.java","lastModified":1640223969740,"locationURI":"file:\/C:\/Users\/Ocean\/Desktop\/HW5\/test_p30\/src\/test_p30\/Sample5_9.java"},{"path":"\/test_p6\/src\/test_p6","parentWorkspace":"C:\/Users\/Ocean\/Desktop\/HW5","name":"Car.java","lastModified":1640222086995,"locationURI":"file:\/C:\/Users\/Ocean\/Desktop\/HW5\/test_p6\/src\/test_p6\/Car.java"},{"path":"\/test_p6\/src\/test_p6","parentWorkspace":"C:\/Users\/Ocean\/Desktop\/HW5","name":"Sample5_1.java","lastModified":1640222087019,"locationURI":"file:\/C:\/Users\/Ocean\/Desktop\/HW5\/test_p6\/src\/test_p6\/Sample5_1.java"},{"path":"\/test_p14\/src\/pb","parentWorkspace":"C:\/Users\/Ocean\/Desktop\/HW5","name":"Sample5_4.java","lastModified":1640222816073,"locationURI":"file:\/C:\/Users\/Ocean\/Desktop\/HW5\/test_p14\/src\/pb\/Sample5_4.java"},{"path":"\/test_p8\/src\/pa","parentWorkspace":"C:\/Users\/Ocean\/Desktop\/HW5","name":"Car.java","lastModified":1640222468470,"locationURI":"file:\/C:\/Users\/Ocean\/Desktop\/HW5\/test_p8\/src\/pa\/Car.java"},{"path":"\/test_p10\/src\/pc","parentWorkspace":"C:\/Users\/Ocean\/Desktop\/HW5","name":"Car.java","lastModified":1640222650905,"locationURI":"file:\/C:\/Users\/Ocean\/Desktop\/HW5\/test_p10\/src\/pc\/Car.java"},{"path":"\/test_p24\/src\/test_p24","parentWorkspace":"C:\/Users\/Ocean\/Desktop\/HW5","name":"Sample5_7.java","lastModified":1640223391870,"locationURI":"file:\/C:\/Users\/Ocean\/Desktop\/HW5\/test_p24\/src\/test_p24\/Sample5_7.java"},{"path":"\/test_p47\/src\/test_p47","parentWorkspace":"C:\/Users\/Ocean\/Desktop\/HW5","name":"Sample5_16.java","lastModified":1640226627299,"locationURI":"file:\/C:\/Users\/Ocean\/Desktop\/HW5\/test_p47\/src\/test_p47\/Sample5_16.java"},{"path":"\/test_p10\/src\/pb","parentWorkspace":"C:\/Users\/Ocean\/Desktop\/HW5","name":"Sample5_3.java","lastModified":1640222650927,"locationURI":"file:\/C:\/Users\/Ocean\/Desktop\/HW5\/test_p10\/src\/pb\/Sample5_3.java"},{"path":"\/test_p50\/src\/test_p50","parentWorkspace":"C:\/Users\/Ocean\/Desktop\/HW5","name":"Sample5_19.java","lastModified":1640227094619,"locationURI":"file:\/C:\/Users\/Ocean\/Desktop\/HW5\/test_p50\/src\/test_p50\/Sample5_19.java"},{"path":"\/test_p19\/src\/test_p19","parentWorkspace":"C:\/Users\/Ocean\/Desktop\/HW5","name":"Sample5_5.java","lastModified":1640223021746,"locationURI":"file:\/C:\/Users\/Ocean\/Desktop\/HW5\/test_p19\/src\/test_p19\/Sample5_5.java"},{"path":"\/test_p34\/src\/test_p34","parentWorkspace":"C:\/Users\/Ocean\/Desktop\/HW5","name":"Sample5_11.java","lastModified":1640225913904,"locationURI":"file:\/C:\/Users\/Ocean\/Desktop\/HW5\/test_p34\/src\/test_p34\/Sample5_11.java"},{"path":"\/test_p55\/src\/test_p55","parentWorkspace":"C:\/Users\/Ocean\/Desktop\/HW5","name":"Sample5_21.java","lastModified":1640227670404,"locationURI":"file:\/C:\/Users\/Ocean\/Desktop\/HW5\/test_p55\/src\/test_p55\/Sample5_21.java"},{"path":"\/test_p45\/src\/test_p45","parentWorkspace":"C:\/Users\/Ocean\/Desktop\/HW5","name":"Sample5_15.java","lastModified":1640226276295,"locationURI":"file:\/C:\/Users\/Ocean\/Desktop\/HW5\/test_p45\/src\/test_p45\/Sample5_15.java"},{"path":"\/test_p40\/src\/test_p40","parentWorkspace":"C:\/Users\/Ocean\/Desktop\/HW5","name":"Sample5_14.java","lastModified":1640225856169,"locationURI":"file:\/C:\/Users\/Ocean\/Desktop\/HW5\/test_p40\/src\/test_p40\/Sample5_14.java"},{"path":"\/test_p32\/src\/test_p32","parentWorkspace":"C:\/Users\/Ocean\/Desktop\/HW5","name":"Sample5_10.java","lastModified":1640224136541,"locationURI":"file:\/C:\/Users\/Ocean\/Desktop\/HW5\/test_p32\/src\/test_p32\/Sample5_10.java"},{"path":"\/test_p35\/src\/test_p35","parentWorkspace":"C:\/Users\/Ocean\/Desktop\/HW5","name":"Sample5_12.java","lastModified":1640224870359,"locationURI":"file:\/C:\/Users\/Ocean\/Desktop\/HW5\/test_p35\/src\/test_p35\/Sample5_12.java"},{"path":"\/test_p8\/src\/pa","parentWorkspace":"C:\/Users\/Ocean\/Desktop\/HW5","name":"Sample5_2.java","lastModified":1640222468490,"locationURI":"file:\/C:\/Users\/Ocean\/Desktop\/HW5\/test_p8\/src\/pa\/Sample5_2.java"},{"path":"\/test_p26\/src\/test_p26","parentWorkspace":"C:\/Users\/Ocean\/Desktop\/HW5","name":"Sample5_8.java","lastModified":1640223506513,"locationURI":"file:\/C:\/Users\/Ocean\/Desktop\/HW5\/test_p26\/src\/test_p26\/Sample5_8.java"},{"path":"\/test_p46\/src\/test_p46","parentWorkspace":"C:\/Users\/Ocean\/Desktop\/HW5","name":"Sample5_16.java","lastModified":1640226422360,"locationURI":"file:\/C:\/Users\/Ocean\/Desktop\/HW5\/test_p46\/src\/test_p46\/Sample5_16.java"}]}